pytest_travis_fold.py
pytest_travis_fold-1.3.0.dist-info/DESCRIPTION.rst
pytest_travis_fold-1.3.0.dist-info/METADATA
pytest_travis_fold-1.3.0.dist-info/RECORD
pytest_travis_fold-1.3.0.dist-info/WHEEL
pytest_travis_fold-1.3.0.dist-info/entry_points.txt
pytest_travis_fold-1.3.0.dist-info/metadata.json
pytest_travis_fold-1.3.0.dist-info/top_level.txt
