Metadata-Version: 2.0
Name: pytest-travis-fold
Version: 1.3.0
Summary: Folds captured output sections in Travis CI build log
Home-page: https://github.com/abusalimov/pytest-travis-fold
Author: Eldar Abusalimov
Author-email: eldar.abusalimov@gmail.com
License: MIT
Keywords: pytest travis build logs continuous integration
Platform: UNKNOWN
Classifier: Development Status :: 4 - Beta
Classifier: Intended Audience :: Developers
Classifier: Topic :: Software Development :: Testing
Classifier: Programming Language :: Python
Classifier: Programming Language :: Python :: 2
Classifier: Programming Language :: Python :: 2.7
Classifier: Programming Language :: Python :: 3
Classifier: Programming Language :: Python :: 3.3
Classifier: Programming Language :: Python :: 3.4
Classifier: Programming Language :: Python :: 3.5
Classifier: Programming Language :: Python :: 3.6
Classifier: Programming Language :: Python :: Implementation :: CPython
Classifier: Programming Language :: Python :: Implementation :: PyPy
Classifier: Operating System :: OS Independent
Classifier: License :: OSI Approved :: MIT License
Requires-Dist: pytest (>=2.6.0)
